zephyr_ml/__init__.py
zephyr_ml/core.py
zephyr_ml/entityset.py
zephyr_ml/feature_engineering.py
zephyr_ml/metadata.py
zephyr_ml/labeling/__init__.py
zephyr_ml/labeling/data_labeler.py
zephyr_ml/labeling/utils.py
zephyr_ml/labeling/labeling_functions/__init__.py
zephyr_ml/labeling/labeling_functions/brake_pad_presence.py
zephyr_ml/labeling/labeling_functions/converter_replacement_presence.py
zephyr_ml/labeling/labeling_functions/planet_bearing.py
zephyr_ml/labeling/labeling_functions/total_power_loss.py
zephyr_ml/pipelines/xgb_classifier.json
zephyr_ml/pipelines/xgb_regressor.json
zephyr_ml/primitives/__init__.py
zephyr_ml/primitives/postprocessing.py
zephyr_ml/primitives/jsons/xgboost.XGBClassifier.json
zephyr_ml/primitives/jsons/xgboost.XGBRegressor.json
zephyr_ml/primitives/jsons/zephyr_ml.primitives.postprocessing.FindThreshold.json
zephyr_ml-0.0.4.dist-info/LICENSE
zephyr_ml-0.0.4.dist-info/METADATA
zephyr_ml-0.0.4.dist-info/WHEEL
zephyr_ml-0.0.4.dist-info/entry_points.txt
zephyr_ml-0.0.4.dist-info/top_level.txt
zephyr_ml-0.0.4.dist-info/RECORD
