Metadata-Version: 2.2
Name: zephyr-ml
Version: 0.0.4
Summary: Prediction engineering methods for Draco.
Home-page: https://github.com/sintel-dev/zephyr
Author: MIT Data To AI Lab
Author-email: dai-lab@mit.edu
Keywords: zephyr Draco Prediction Engineering
Classifier: Development Status :: 2 - Pre-Alpha
Classifier: Intended Audience :: Developers
Classifier: Natural Language :: English
Classifier: Programming Language :: Python :: 3
Classifier: Programming Language :: Python :: 3.8
Classifier: Programming Language :: Python :: 3.9
Classifier: Programming Language :: Python :: 3.10
Classifier: Programming Language :: Python :: 3.11
Classifier: Programming Language :: Python :: 3.12
Requires-Python: >=3.8,<3.13
License-File: LICENSE
Requires-Dist: numpy<1.27.0,>=1.19.5
Requires-Dist: pandas<2,>=1
Requires-Dist: composeml<0.10,>=0.1.6
Requires-Dist: featuretools<2.0.0,>=1.0.0
Requires-Dist: mlblocks<0.7,>=0.6.0
Requires-Dist: sigpro>=0.2.0
Requires-Dist: xgboost<1,>=0.72.1
Requires-Dist: jupyter==1.0.0
Provides-Extra: test
Requires-Dist: pytest>=3.4.2; extra == "test"
Requires-Dist: pytest-cov>=2.6.0; extra == "test"
Requires-Dist: jupyter<2,>=1.0.0; extra == "test"
Requires-Dist: rundoc<0.5,>=0.4.3; extra == "test"
Requires-Dist: invoke; extra == "test"
Provides-Extra: dev
Requires-Dist: bumpversion<0.6,>=0.5.3; extra == "dev"
Requires-Dist: pip>=9.0.1; extra == "dev"
Requires-Dist: watchdog<0.11,>=0.8.3; extra == "dev"
Requires-Dist: docutils<0.18,>=0.12; extra == "dev"
Requires-Dist: lxml_html_clean>=0.2.2; extra == "dev"
Requires-Dist: m2r2<0.3,>=0.2.5; extra == "dev"
Requires-Dist: nbsphinx<0.7,>=0.5.0; extra == "dev"
Requires-Dist: Sphinx<3.3,>=3; extra == "dev"
Requires-Dist: sphinx_rtd_theme<0.5,>=0.2.4; extra == "dev"
Requires-Dist: autodocsumm>=0.1.10; extra == "dev"
Requires-Dist: mistune<2,>=0.7; extra == "dev"
Requires-Dist: Jinja2<3.1,>=2; extra == "dev"
Requires-Dist: alabaster<=0.7.12; extra == "dev"
Requires-Dist: sphinxcontrib-applehelp<1.0.8; extra == "dev"
Requires-Dist: sphinxcontrib-devhelp<1.0.6; extra == "dev"
Requires-Dist: sphinxcontrib-htmlhelp<2.0.5; extra == "dev"
Requires-Dist: sphinxcontrib-serializinghtml<1.1.10; extra == "dev"
Requires-Dist: sphinxcontrib-qthelp<1.0.7; extra == "dev"
Requires-Dist: flake8<4,>=3.7.7; extra == "dev"
Requires-Dist: isort<5,>=4.3.4; extra == "dev"
Requires-Dist: autoflake<2,>=1.1; extra == "dev"
Requires-Dist: autopep8<2,>=1.4.3; extra == "dev"
Requires-Dist: twine<4,>=1.10.0; extra == "dev"
Requires-Dist: wheel>=0.30.0; extra == "dev"
Requires-Dist: coverage<6,>=4.5.1; extra == "dev"
Requires-Dist: tox<4,>=2.9.1; extra == "dev"
Requires-Dist: jupyter>=1.0.0; extra == "dev"
Requires-Dist: pytest>=3.4.2; extra == "dev"
Requires-Dist: pytest-cov>=2.6.0; extra == "dev"
Requires-Dist: jupyter<2,>=1.0.0; extra == "dev"
Requires-Dist: rundoc<0.5,>=0.4.3; extra == "dev"
Requires-Dist: invoke; extra == "dev"
Dynamic: author
Dynamic: author-email
Dynamic: classifier
Dynamic: description
Dynamic: description-content-type
Dynamic: home-page
Dynamic: keywords
Dynamic: provides-extra
Dynamic: requires-dist
Dynamic: requires-python
Dynamic: summary
